{"BusinessCombinationConsiderationTransferredEquityInterestsIssuedAndIssuableNumberOfSharesSubjectToAnIndemnityHoldback":[{"decimals":"0","unitRef":"shares","period":{"startDate":"2022-01-04","endDate":"2022-01-04"},"segment":[{"dimension":"us-gaap:BusinessAcquisitionAxis","value":"coin:UnboundSecurityIncMember"},{"dimension":"us-gaap:EquityInterestIssuedOrIssuableByTypeAxis","value":"us-gaap:CommonClassAMember"}],"value":"85324"},{"decimals":"0","unitRef":"shares","period":{"startDate":"2022-02-01","endDate":"2022-02-01"},"segment":[{"dimension":"us-gaap:BusinessAcquisitionAxis","value":"coin:FairXchangeIncMember"},{"dimension":"us-gaap:EquityInterestIssuedOrIssuableByTypeAxis","value":"us-gaap:CommonClassAMember"}],"value":"83035"},{"decimals":"INF","unitRef":"shares","period":{"startDate":"2021-02-08","endDate":"2021-02-08"},"segment":[{"dimension":"us-gaap:BusinessAcquisitionAxis","value":"coin:BisonTrailsCoMember"},{"dimension":"us-gaap:EquityInterestIssuedOrIssuableByTypeAxis","value":"us-gaap:CommonClassAMember"}],"value":"496434"}]}