{"AccountsNotesAndLoansReceivableNetCurrent":[{"decimals":"-3","unitRef":"usd","period":{"instant":"2022-12-31"},"value":"404376000"},{"decimals":"-3","unitRef":"usd","period":{"instant":"2021-12-31"},"value":"304706000"},{"decimals":"-3","unitRef":"usd","period":{"instant":"2021-12-31"},"segment":{"dimension":"srt:RestatementAxis","value":"srt:ScenarioPreviouslyReportedMember"},"value":"396025000"},{"decimals":"-3","unitRef":"usd","period":{"instant":"2021-12-31"},"segment":{"dimension":"srt:RestatementAxis","value":"srt:RevisionOfPriorPeriodChangeInAccountingPrincipleAdjustmentMember"},"value":"-91319000"}]}