[{"decimals":"-3","unitRef":"shares","period":{"instant":"2021-12-31"},"segment":{"dimension":"us-gaap:StatementClassOfStockAxis","value":"us-gaap:CommonClassAMember"},"value":"10000000000"},{"decimals":"-3","unitRef":"shares","period":{"instant":"2022-09-30"},"segment":{"dimension":"us-gaap:StatementClassOfStockAxis","value":"us-gaap:CommonClassAMember"},"value":"10000000000"},{"decimals":"-3","unitRef":"shares","period":{"instant":"2022-09-30"},"segment":{"dimension":"us-gaap:StatementClassOfStockAxis","value":"us-gaap:CommonClassBMember"},"value":"500000000"},{"decimals":"-3","unitRef":"shares","period":{"instant":"2021-12-31"},"segment":{"dimension":"us-gaap:StatementClassOfStockAxis","value":"us-gaap:CommonClassBMember"},"value":"500000000"},{"decimals":"0","unitRef":"shares","period":{"instant":"2021-04-01"},"segment":{"dimension":"us-gaap:StatementClassOfStockAxis","value":"us-gaap:CommonClassAMember"},"value":"10000000000"},{"decimals":"0","unitRef":"shares","period":{"instant":"2021-04-01"},"segment":{"dimension":"us-gaap:StatementClassOfStockAxis","value":"us-gaap:CommonClassBMember"},"value":"500000000"},{"decimals":"0","unitRef":"shares","period":{"instant":"2021-04-01"},"segment":{"dimension":"us-gaap:StatementClassOfStockAxis","value":"coin:UndesignatedCommonStockMember"},"value":"500000000"},{"decimals":"0","unitRef":"shares","period":{"instant":"2021-04-01"},"segment":{"dimension":"us-gaap:StatementClassOfStockAxis","value":"coin:UndesignatedPreferredStockMember"},"value":"500000000"}]