{"BusinessCombinationRecognizedIdentifiableAssetsAcquiredAndLiabilitiesAssumedLiabilities":[{"decimals":"-3","unitRef":"usd","period":{"instant":"2022-01-04"},"segment":{"dimension":"us-gaap:BusinessAcquisitionAxis","value":"coin:UnboundSecurityIncMember"},"value":"19327000"},{"decimals":"-3","unitRef":"usd","period":{"instant":"2022-02-01"},"segment":{"dimension":"us-gaap:BusinessAcquisitionAxis","value":"coin:FairXchangeIncMember"},"value":"17188000"},{"decimals":"-3","unitRef":"usd","period":{"instant":"2021-02-08"},"segment":{"dimension":"us-gaap:BusinessAcquisitionAxis","value":"coin:BisonTrailsCoMember"},"value":"7851000"},{"decimals":"-3","unitRef":"usd","period":{"instant":"2021-12-31"},"segment":{"dimension":"us-gaap:BusinessAcquisitionAxis","value":"us-gaap:SeriesOfIndividuallyImmaterialBusinessAcquisitionsMember"},"value":"3847000"},{"decimals":"-3","unitRef":"usd","period":{"instant":"2020-07-31"},"segment":{"dimension":"us-gaap:BusinessAcquisitionAxis","value":"coin:TagomiHoldingsIncMember"},"value":"35414000"}]}