{"IncreaseDecreaseInReceivables":[{"decimals":"-3","unitRef":"usd","period":{"startDate":"2022-01-01","endDate":"2022-12-31"},"value":"141023000"},{"decimals":"-3","unitRef":"usd","period":{"startDate":"2021-01-01","endDate":"2021-12-31"},"value":"-28511000"},{"decimals":"-3","unitRef":"usd","period":{"startDate":"2020-01-01","endDate":"2020-12-31"},"value":"117167000"},{"decimals":"-3","unitRef":"usd","period":{"startDate":"2021-01-01","endDate":"2021-12-31"},"segment":{"dimension":"srt:RestatementAxis","value":"srt:ScenarioPreviouslyReportedMember"},"value":"8016000"},{"decimals":"-3","unitRef":"usd","period":{"startDate":"2021-01-01","endDate":"2021-12-31"},"segment":{"dimension":"srt:RestatementAxis","value":"srt:RevisionOfPriorPeriodChangeInAccountingPrincipleAdjustmentMember"},"value":"-36527000"},{"decimals":"-3","unitRef":"usd","period":{"startDate":"2020-01-01","endDate":"2020-12-31"},"segment":{"dimension":"srt:RestatementAxis","value":"srt:ScenarioPreviouslyReportedMember"},"value":"157156000"},{"decimals":"-3","unitRef":"usd","period":{"startDate":"2020-01-01","endDate":"2020-12-31"},"segment":{"dimension":"srt:RestatementAxis","value":"srt:RevisionOfPriorPeriodChangeInAccountingPrincipleAdjustmentMember"},"value":"-39989000"}]}